eco4cast/__init__.py
eco4cast/master_machine/__init__.py
eco4cast/master_machine/co2_model.py
eco4cast/master_machine/compute/README.md
eco4cast/master_machine/compute/client_library/README.md
eco4cast/master_machine/compute/client_library/__init__.py
eco4cast/master_machine/compute/client_library/ingredients/__init__.py
eco4cast/master_machine/compute/client_library/ingredients/disks/attach_disk.py
eco4cast/master_machine/compute/client_library/ingredients/disks/autodelete_change.py
eco4cast/master_machine/compute/client_library/ingredients/disks/clone_encrypted_disk.py
eco4cast/master_machine/compute/client_library/ingredients/disks/clone_encrypted_disk_managed_key.py
eco4cast/master_machine/compute/client_library/ingredients/disks/create_empty_disk.py
eco4cast/master_machine/compute/client_library/ingredients/disks/create_from_image.py
eco4cast/master_machine/compute/client_library/ingredients/disks/create_from_snapshot.py
eco4cast/master_machine/compute/client_library/ingredients/disks/create_from_source.py
eco4cast/master_machine/compute/client_library/ingredients/disks/create_kms_encrypted_disk.py
eco4cast/master_machine/compute/client_library/ingredients/disks/delete.py
eco4cast/master_machine/compute/client_library/ingredients/disks/disk_from_snapshot.py
eco4cast/master_machine/compute/client_library/ingredients/disks/empty_disk.py
eco4cast/master_machine/compute/client_library/ingredients/disks/from_image.py
eco4cast/master_machine/compute/client_library/ingredients/disks/get.py
eco4cast/master_machine/compute/client_library/ingredients/disks/list.py
eco4cast/master_machine/compute/client_library/ingredients/disks/local_ssd.py
eco4cast/master_machine/compute/client_library/ingredients/disks/regional_create_from_source.py
eco4cast/master_machine/compute/client_library/ingredients/disks/regional_delete.py
eco4cast/master_machine/compute/client_library/ingredients/disks/resize_disk.py
eco4cast-0.0.8.dist-info/LICENSE
eco4cast-0.0.8.dist-info/METADATA
eco4cast-0.0.8.dist-info/WHEEL
eco4cast-0.0.8.dist-info/RECORD
