Metadata-Version: 2.1
Name: eco4cast
Version: 0.0.8
Summary: This package is designed to reduce CO2 emissions while training neural networks using Google Cloud.
Home-page: https://github.com/AIRI-Institute/eco4cast
Keywords: co2 emission,google cloud,pytorch
Author: Mikhail Tiutiulnikov
Author-email: tiutiulnikov@airi.net
Requires-Python: >=3.9,<4.0
Classifier: Programming Language :: Python :: 3
Classifier: Programming Language :: Python :: 3.9
Classifier: Programming Language :: Python :: 3.10
Classifier: Programming Language :: Python :: 3.11
Requires-Dist: apscheduler (>=3.10.1,<4.0.0)
Requires-Dist: eco2ai (>=0.3.9,<0.4.0)
Requires-Dist: google-cloud-compute (>=1.11.0,<2.0.0)
Requires-Dist: lightning (>=2.0.2,<3.0.0)
Requires-Dist: numpy (>=1.23.5)
Requires-Dist: pandas (>=1.4.3)
Requires-Dist: paramiko (>=3.2.0,<4.0.0)
Requires-Dist: scikit-learn (>=1.2.2,<2.0.0)
Requires-Dist: torch (>=2.0.1,<3.0.0)
Project-URL: Repository, https://github.com/AIRI-Institute/eco4cast
